Workbook

Sheet Dashboard
A1: Household Financial Dashboard
A3: Annual Income | C3: Annual Spending | E3: Net Cash Flow | G3: Custom Health Score
A4: ='Financial Health'!B4 -> 174923.04 | C4: ='Financial Health'!B5 -> 371758.32 | E4: ='Financial Health'!B6 -> -196835.28 | G4: ='Financial Health'!B10 -> 40
G5: * custom project metric (not industry-standard score)
F75: Key Insights
F76: • Travel is the largest spending category, accounting for about 41.4% of annual spending.
F77: • March and October were the highest-spending months relative to the monthly average.
F78: • Credit cards represent a relatively small share of debt principal but a disproportionately high share of estimated interest cost.
F79: • The household has negative annual cash flow and would require major discretionary spending cuts, income growth, or both to reach break-even.

Sheet Spending Summary
A1: Spending Summary
A3: Category | B3: Annual Spending | C3: % of total
A4: Travel | B4: 153896.94 | C4: =B4/SUM($B$4:B$12) -> 0.4139704
A5: Shopping | B5: 57362.35 | C5: =B5/SUM($B$4:B$12) -> 0.15430011
A6: Utilities | B6: 45461.06 | C6: =B6/SUM($B$4:B$12) -> 0.1222866
A7: Housing | B7: 34200 | C7: =B7/SUM($B$4:B$12) -> 0.091995251
A8: Groceries | B8: 31541.5 | C8: =B8/SUM($B$4:B$12) -> 0.0848441
A9: Transportation | B9: 19363.47 | C9: =B9/SUM($B$4:B$12) -> 0.052086178
A10: Dining | B10: 13152.43 | C10: =B10/SUM($B$4:B$12) -> 0.03537898
A11: Entertainment | B11: 11750.69 | C11: =B11/SUM($B$4:B$12) -> 0.031608412
A12: Fitness | B12: 5029.88 | C12: =B12/SUM($B$4:B$12) -> 0.013529973
A15: Month | B15: Monthly Spending | C15: % vs Average | D15: Spending Flag
A16: Jan | B16: 29194.28 | C16: =(B16-$B$29)/$B$29 -> -0.0576368 | D16: =IF(C16>=10%, "High", "Normal") -> Normal
A17: Feb | B17: 30229.09 | C17: =(B17-$B$29)/$B$29 -> -0.024234131 | D17: =IF(C17>=10%, "High", "Normal") -> Normal
A18: Mar | B18: 34800.93 | C18: =(B18-$B$29)/$B$29 -> 0.12334045 | D18: =IF(C18>=10%, "High", "Normal") -> High
A19: Apr | B19: 29447.16 | C19: =(B19-$B$29)/$B$29 -> -0.049474078 | D19: =IF(C19>=10%, "High", "Normal") -> Normal
A20: May | B20: 28793.76 | C20: =(B20-$B$29)/$B$29 -> -0.070565199 | D20: =IF(C20>=10%, "High", "Normal") -> Normal
A21: Jun | B21: 30765.25 | C21: =(B21-$B$29)/$B$29 -> -0.0069274038 | D21: =IF(C21>=10%, "High", "Normal") -> Normal
A22: Jul | B22: 27035.42 | C22: =(B22-$B$29)/$B$29 -> -0.12732272 | D22: =IF(C22>=10%, "High", "Normal") -> Normal
A23: Aug | B23: 33698.04 | C23: =(B23-$B$29)/$B$29 -> 0.087740229 | D23: =IF(C23>=10%, "High", "Normal") -> Normal
A24: Sep | B24: 30222.67 | C24: =(B24-$B$29)/$B$29 -> -0.024441363 | D24: =IF(C24>=10%, "High", "Normal") -> Normal
A25: Oct | B25: 34376.61 | C25: =(B25-$B$29)/$B$29 -> 0.10964381 | D25: =IF(C25>=10%, "High", "Normal") -> High
A26: Nov | B26: 31212.49 | C26: =(B26-$B$29)/$B$29 -> 0.007509072 | D26: =IF(C26>=10%, "High", "Normal") -> Normal
A27: Dec | B27: 31982.62 | C27: =(B27-$B$29)/$B$29 -> 0.032368126 | D27: =IF(C27>=10%, "High", "Normal") -> Normal
A29: Avg Monthly Spending: | B29: =AVERAGE(B16:B27) -> 30979.86

Sheet Debt Analysis
A1: Debt Analysis
A3: Lender | B3: Debt Type | C3: Balance | D3: APR | E3: Minimum Payment
A4: Chase | B4: Credit Card | C4: 8400 | D4: 0.2499 | E4: 252
A5: Capital One | B5: Credit Card | C5: 3200 | D5: 0.2049 | E5: 96
A6: Desert Auto Finance | B6: Auto Loan | C6: 22600 | D6: 0.0675 | E6: 552
A7: Federal Student Aid - Alex | B7: Student Loan | C7: 31500 | D7: 0.052 | E7: 338
A8: Federal Student Aid - Jordan | B8: Student Loan | C8: 18000 | D8: 0.044 | E8: 205
A10: Total Listed Debt | C10: =SUM(Table3[Balance]) -> 83700
A11: Weighted Average APR | D11: {=SUMPRODUCT(Table3[Balance],Table3[APR]/SUM(Table3[Balance]))} -> 0.080171326
A12: Total Monthly Minimum Payments | E12: =SUM(Table3[Minimum Payment]) -> 1443
A14: Missing Amex Balance | C14: 1850
A15: Adjusted Total Debt | C15: =C10+C14 -> 85550
A17: Checking Cash | C17: 19000
A18: Cash-to-Debt Ration | C18: =C17/C15 -> 0.22209234
A19: Net Liquid Position | C19: =C17-C15 -> -66550
A20: Annual Income | C20: 174923.04
A21: Debt-to-Income | C21: =C15/C20 -> 0.48907222

Sheet Financial Health
A1: Financial Health
A3: Metric | B3: Value
A4: Annual Income | B4: ='Debt Analysis'!C20 -> 174923.04
A5: Annual Spending | B5: =SUM('Spending Summary'!B4:B12) -> 371758.32
A6: Annual Net Cash Flow | B6: =B4-B5 -> -196835.28
A7: Cash Flow Mragin | B7: =B6/B4 -> -1.1252679
A8: Cash-to-Debt Ratio | B8: ='Debt Analysis'!C18 -> 0.22209234
A9: Debt-to-Income | B9: ='Debt Analysis'!C21 -> 0.48907222
A10: Custom Financial Health Score | B10: =100-(COUNTIF(B6,"<0")*20)-(IF(B8<25%,20,0))-(IF(B9>40%,20,0)) -> 40
A12: Risk Flags
A13: Negative Annual Cash Flow | B13: =IF(B6<0,"Flag","OK") -> Flag
A14: Low Cash Coverage Relative to Debt | B14: =IF(B8<25%,"Flag","OK") -> Flag
A15: High Total Debt Relative to Annual Income | B15: =IF(B9>40%,"Flag","OK") -> Flag
